Paginator/Paginate.py
Paginator/__init__.py
disnake_pagination-2.1.dist-info/LICENSE
disnake_pagination-2.1.dist-info/METADATA
disnake_pagination-2.1.dist-info/WHEEL
disnake_pagination-2.1.dist-info/top_level.txt
disnake_pagination-2.1.dist-info/RECORD
