Metadata-Version: 2.1
Name: disnake-pagination
Version: 2.1
Summary: A simple Embed Paginator for your projects made with disnake.
Home-page: https://github.com/DorianAarno/Paginator
Author: Aarno Dorian
Author-email: aarnodorian56@gmail.com
License: MIT
Download-URL: https://github.com/DorianAarno/Paginator/archive/refs/tags/v2.1.tar.gz
Platform: UNKNOWN
Classifier: Intended Audience :: Developers
Classifier: Natural Language :: English
Classifier: Operating System :: OS Independent
Classifier: Programming Language :: Python :: 3.8
Classifier: Programming Language :: Python :: 3.9
Classifier: Programming Language :: Python :: 3.10
Classifier: Topic :: Internet
Classifier: Topic :: Software Development :: Libraries
Classifier: Topic :: Software Development :: Libraries :: Python Modules
Classifier: Topic :: Utilities
Classifier: Typing :: Typed
License-File: LICENSE
Requires-Dist: disnake
